CHANGELOG
COPYRIGHT
INSTALL
LICENSE
MANIFEST.in
README
TODO
sale.xml
setup.py
shop.xml
tryton.cfg
user.xml
./__init__.py
./sale.py
./shop.py
./stock.py
./user.py
./tests/__init__.py
./tests/test_sale_shop.py
doc/INSTALL
doc/index.rst
locale/ca_ES.po
locale/de_DE.po
locale/es_ES.po
locale/fr_FR.po
tests/scenario_sale_shop.rst
trytonzz_sale_shop.egg-info/PKG-INFO
trytonzz_sale_shop.egg-info/SOURCES.txt
trytonzz_sale_shop.egg-info/dependency_links.txt
trytonzz_sale_shop.egg-info/entry_points.txt
trytonzz_sale_shop.egg-info/not-zip-safe
trytonzz_sale_shop.egg-info/requires.txt
trytonzz_sale_shop.egg-info/top_level.txt
view/sale_form.xml
view/sale_shop_form.xml
view/sale_shop_tree.xml
view/sale_tree.xml
view/user_form.xml
view/user_form_preferences.xml